{
"type": "FeatureCollection",
"crs": { "type": "name", "properties": { "name": "urn:ogc:def:crs:OGC:1.3:CRS84" } },
"features": [
{ "type": "Feature", "properties": { "Gauge": "OneRain12009", "corr": 0.85, "MAE": 0.4, "RMSE": 0.56 }, "geometry": { "type": "Point", "coordinates": [ -93.422098616295258, 30.138984025300559 ] } },
{ "type": "Feature", "properties": { "Gauge": "OneRain12023", "corr": 0.87, "MAE": 0.68, "RMSE": 0.92 }, "geometry": { "type": "Point", "coordinates": [ -93.426721995678349, 30.168505168063152 ] } },
{ "type": "Feature", "properties": { "Gauge": "OneRain12024", "corr": 0.93, "MAE": 0.85, "RMSE": 1.29 }, "geometry": { "type": "Point", "coordinates": [ -93.439590928618571, 30.227305224187013 ] } },
{ "type": "Feature", "properties": { "Gauge": "OneRain12044", "corr": 0.95, "MAE": 0.71, "RMSE": 0.82 }, "geometry": { "type": "Point", "coordinates": [ -93.46918384335109, 30.275593751492057 ] } },
{ "type": "Feature", "properties": { "Gauge": "OneRain12058", "corr": 0.92, "MAE": 0.65, "RMSE": 0.81 }, "geometry": { "type": "Point", "coordinates": [ -93.41834028844427, 30.188344591469022 ] } },
{ "type": "Feature", "properties": { "Gauge": "OneRain12059", "corr": 0.88, "MAE": 0.63, "RMSE": 0.93 }, "geometry": { "type": "Point", "coordinates": [ -93.40439141731494, 30.175989967311057 ] } },
{ "type": "Feature", "properties": { "Gauge": "OneRain12061", "corr": 0.96, "MAE": 0.25, "RMSE": 0.49 }, "geometry": { "type": "Point", "coordinates": [ -93.403599587613243, 30.15408044769692 ] } },
{ "type": "Feature", "properties": { "Gauge": "OneRain12115", "corr": 0.94, "MAE": 1.0, "RMSE": 1.03 }, "geometry": { "type": "Point", "coordinates": [ -93.487999999894441, 30.231197600001714 ] } },
{ "type": "Feature", "properties": { "Gauge": "OneRain12118", "corr": 0.91, "MAE": 0.33, "RMSE": 0.44 }, "geometry": { "type": "Point", "coordinates": [ -93.43495520751695, 30.130699089682977 ] } },
{ "type": "Feature", "properties": { "Gauge": "OneRain12120", "corr": 0.85, "MAE": 1.13, "RMSE": 1.26 }, "geometry": { "type": "Point", "coordinates": [ -93.439030576287834, 30.182819037861414 ] } }
]
}
