{
"type": "FeatureCollection",
"crs": { "type": "name", "properties": { "name": "urn:ogc:def:crs:OGC:1.3:CRS84" } },
"features": [
{ "type": "Feature", "properties": { "Gauge": "OneRain 12006", "FID": 0, "corr": 0.94, "MAE": 0.65, "RMSE": 0.77 }, "geometry": { "type": "Point", "coordinates": [ -93.122066050913105, 30.261443308343544 ] } },
{ "type": "Feature", "properties": { "Gauge": "OneRain 12010", "FID": 1, "corr": 0.98, "MAE": 0.67, "RMSE": 0.84 }, "geometry": { "type": "Point", "coordinates": [ -93.019365481942685, 30.241148581413576 ] } },
{ "type": "Feature", "properties": { "Gauge": "OneRain 12011", "FID": 2, "corr": 0.97, "MAE": 1.15, "RMSE": 1.4 }, "geometry": { "type": "Point", "coordinates": [ -93.080865016088808, 30.240701258791113 ] } },
{ "type": "Feature", "properties": { "Gauge": "OneRain 12014", "FID": 3, "corr": 0.87, "MAE": 0.69, "RMSE": 1.17 }, "geometry": { "type": "Point", "coordinates": [ -93.065596883422486, 30.308354334830963 ] } },
{ "type": "Feature", "properties": { "Gauge": "OneRain 12015", "FID": 4, "corr": 0.95, "MAE": 0.45, "RMSE": 0.7 }, "geometry": { "type": "Point", "coordinates": [ -93.095488573309154, 30.290643997065505 ] } },
{ "type": "Feature", "properties": { "Gauge": "OneRain 12079", "FID": 5, "corr": 0.94, "MAE": 0.66, "RMSE": 0.79 }, "geometry": { "type": "Point", "coordinates": [ -93.071654183092491, 30.330317982890811 ] } },
{ "type": "Feature", "properties": { "Gauge": "OneRain 12080", "FID": 6, "corr": 0.99, "MAE": 0.3, "RMSE": 0.4 }, "geometry": { "type": "Point", "coordinates": [ -93.05851959403887, 30.287392977260378 ] } },
{ "type": "Feature", "properties": { "Gauge": "OneRain 12081", "FID": 7, "corr": 0.98, "MAE": 0.43, "RMSE": 0.54 }, "geometry": { "type": "Point", "coordinates": [ -93.081300835873108, 30.277932399428519 ] } },
{ "type": "Feature", "properties": { "Gauge": "OneRain 12082", "FID": 8, "corr": 0.97, "MAE": 0.44, "RMSE": 0.51 }, "geometry": { "type": "Point", "coordinates": [ -93.129615079931781, 30.248562857828908 ] } },
{ "type": "Feature", "properties": { "Gauge": "OneRain 12083", "FID": 9, "corr": 0.96, "MAE": 1.71, "RMSE": 2.06 }, "geometry": { "type": "Point", "coordinates": [ -93.068179890606544, 30.236693255898121 ] } },
{ "type": "Feature", "properties": { "Gauge": "OneRain 12084", "FID": 10, "corr": 0.92, "MAE": 1.36, "RMSE": 1.86 }, "geometry": { "type": "Point", "coordinates": [ -93.038716814891572, 30.218166012869997 ] } },
{ "type": "Feature", "properties": { "Gauge": "OneRain 12129 DS", "FID": 11, "corr": 0.97, "MAE": 0.46, "RMSE": 0.65 }, "geometry": { "type": "Point", "coordinates": [ -93.136656228818424, 30.243366011150272 ] } },
{ "type": "Feature", "properties": { "Gauge": "OneRain 12126", "FID": 12, "corr": 0.95, "MAE": 0.72, "RMSE": 1.11 }, "geometry": { "type": "Point", "coordinates": [ -93.086371524463374, 30.21805865687038 ] } },
{ "type": "Feature", "properties": { "Gauge": "OneRain 12129 US", "FID": 13, "corr": 0.65, "MAE": 1.06, "RMSE": 1.56 }, "geometry": { "type": "Point", "coordinates": [ -93.136634087172823, 30.243153214126938 ] } }
]
}
