{
"type": "FeatureCollection",
"crs": { "type": "name", "properties": { "name": "urn:ogc:def:crs:OGC:1.3:CRS84" } },
"features": [
{ "type": "Feature", "properties": { "Gauge": "USGS 8017044", "FID": 2, "corr": 1.0, "MAE": 0.05, "RMSE": 0.07 }, "geometry": { "type": "Point", "coordinates": [ -93.247170630150137, 30.23771962612793, 0.0 ] } },
{ "type": "Feature", "properties": { "Gauge": "OneRain 12084", "FID": 7, "corr": 0.91, "MAE": 3.49, "RMSE": 3.64 }, "geometry": { "type": "Point", "coordinates": [ -93.038716217893523, 30.218187245207215, 16.0 ] } },
{ "type": "Feature", "properties": { "Gauge": "OneRain 12069", "FID": 5, "corr": 0.48, "MAE": 0.53, "RMSE": 0.74 }, "geometry": { "type": "Point", "coordinates": [ -93.174550603612801, 30.227460795253307, 7.0 ] } },
{ "type": "Feature", "properties": { "Gauge": "OneRain 12011", "FID": 6, "corr": 0.36, "MAE": 0.47, "RMSE": 0.78 }, "geometry": { "type": "Point", "coordinates": [ -93.080980465597833, 30.240677087013019, 13.0 ] } },
{ "type": "Feature", "properties": { "Gauge": "OneRain 12082", "FID": 13, "corr": 0.9, "MAE": 1.62, "RMSE": 1.66 }, "geometry": { "type": "Point", "coordinates": [ -93.12957495084845, 30.248589241649373, 16.0 ] } },
{ "type": "Feature", "properties": { "Gauge": "OneRain 12006", "FID": 14, "corr": 0.85, "MAE": 1.34, "RMSE": 1.51 }, "geometry": { "type": "Point", "coordinates": [ -93.122088583001116, 30.261420298375402, 9.0 ] } },
{ "type": "Feature", "properties": { "Gauge": "OneRain 12037", "FID": 15, "corr": 0.94, "MAE": 1.22, "RMSE": 1.25 }, "geometry": { "type": "Point", "coordinates": [ -93.172275622732883, 30.263827303232588, 17.0 ] } },
{ "type": "Feature", "properties": { "Gauge": "OneRain 12081", "FID": 11, "corr": 0.9, "MAE": 1.49, "RMSE": 1.68 }, "geometry": { "type": "Point", "coordinates": [ -93.081464941836373, 30.277908550403833, 16.0 ] } },
{ "type": "Feature", "properties": { "Gauge": "OneRain 12015", "FID": 12, "corr": 0.79, "MAE": 0.89, "RMSE": 1.32 }, "geometry": { "type": "Point", "coordinates": [ -93.09552395028318, 30.290627197060939, 12.0 ] } },
{ "type": "Feature", "properties": { "Gauge": "OneRain 12080", "FID": 13, "corr": 0.97, "MAE": 1.6, "RMSE": 1.99 }, "geometry": { "type": "Point", "coordinates": [ -93.058483167499034, 30.287309156891332, 15.0 ] } },
{ "type": "Feature", "properties": { "Gauge": "OneRain 12014", "FID": 21, "corr": 0.72, "MAE": 7.75, "RMSE": 7.88 }, "geometry": { "type": "Point", "coordinates": [ -93.065606109816926, 30.308330349984438, 13.0 ] } },
{ "type": "Feature", "properties": { "Gauge": "OneRain 12016", "FID": 16, "corr": 0.86, "MAE": 2.02, "RMSE": 2.03 }, "geometry": { "type": "Point", "coordinates": [ -93.170111720531878, 30.329002937496373, 26.0 ] } },
{ "type": "Feature", "properties": { "Gauge": "OneRain 12079", "FID": 23, "corr": 0.74, "MAE": 1.88, "RMSE": 2.34 }, "geometry": { "type": "Point", "coordinates": [ -93.071762634712073, 30.330275845960102, 10.0 ] } },
{ "type": "Feature", "properties": { "Gauge": "OneRain 12018", "FID": 18, "corr": 0.63, "MAE": 0.72, "RMSE": 0.78 }, "geometry": { "type": "Point", "coordinates": [ -93.152030348775654, 30.398313704927808, 19.0 ] } },
{ "type": "Feature", "properties": { "Gauge": "OneRain 12077", "FID": 19, "corr": 0.6, "MAE": 0.82, "RMSE": 1.18 }, "geometry": { "type": "Point", "coordinates": [ -93.205075956845931, 30.300453717772715, 15.0 ] } },
{ "type": "Feature", "properties": { "Gauge": "OneRain 12078", "FID": 27, "corr": 0.81, "MAE": 2.37, "RMSE": 2.48 }, "geometry": { "type": "Point", "coordinates": [ -93.178842802240112, 30.302560294599495, 7.0 ] } },
{ "type": "Feature", "properties": { "Gauge": "OneRain 12068", "FID": 21, "corr": 0.93, "MAE": 1.78, "RMSE": 1.88 }, "geometry": { "type": "Point", "coordinates": [ -93.168379464540749, 30.176700322739432, 13.0 ] } },
{ "type": "Feature", "properties": { "Gauge": "OneRain 12070", "FID": 31, "corr": 0.82, "MAE": 2.75, "RMSE": 2.77 }, "geometry": { "type": "Point", "coordinates": [ -93.251294065010129, 30.262972592830003, 5.0 ] } }
]
}
