{
"type": "FeatureCollection",
"crs": { "type": "name", "properties": { "name": "urn:ogc:def:crs:OGC:1.3:CRS84" } },
"features": [
{ "type": "Feature", "properties": { "Gauge": "CRMS2219", "corr": 0.89, "MAE": 0.81, "RMSE": 0.84, "NSE": -2.21 }, "geometry": { "type": "Point", "coordinates": [ -93.604321886716548, 29.766388686269242 ] } },
{ "type": "Feature", "properties": { "Gauge": "CRMS0680", "corr": 0.99, "MAE": 0.67, "RMSE": 0.7, "NSE": -0.57 }, "geometry": { "type": "Point", "coordinates": [ -93.510570675568374, 29.773647105180537 ] } },
{ "type": "Feature", "properties": { "Gauge": "CRMS1838", "corr": 0.92, "MAE": 0.92, "RMSE": 0.94, "NSE": -3.9 }, "geometry": { "type": "Point", "coordinates": [ -93.698073654227059, 29.780903420355003 ] } },
{ "type": "Feature", "properties": { "Gauge": "CRMS0682", "corr": 0.85, "MAE": 0.71, "RMSE": 0.75, "NSE": -2.13 }, "geometry": { "type": "Point", "coordinates": [ -93.573072430652317, 29.824452550821803 ] } },
{ "type": "Feature", "properties": { "Gauge": "CRMS1858", "corr": 0.99, "MAE": 0.75, "RMSE": 0.77, "NSE": -2.03 }, "geometry": { "type": "Point", "coordinates": [ -93.510570997117838, 29.838970091658929 ] } },
{ "type": "Feature", "properties": { "Gauge": "CRMS0647", "corr": 0.89, "MAE": 0.57, "RMSE": 0.61, "NSE": -0.65 }, "geometry": { "type": "Point", "coordinates": [ -93.479320670517311, 29.846227964686118 ] } },
{ "type": "Feature", "properties": { "Gauge": "CRMS0661", "corr": 0.94, "MAE": 0.99, "RMSE": 1.02, "NSE": -2.27 }, "geometry": { "type": "Point", "coordinates": [ -93.635573620313806, 29.846227182386631 ] } },
{ "type": "Feature", "properties": { "Gauge": "CRMS0642", "corr": 0.93, "MAE": 0.52, "RMSE": 0.57, "NSE": 0.82 }, "geometry": { "type": "Point", "coordinates": [ -93.479320528803598, 29.868002180295473 ] } },
{ "type": "Feature", "properties": { "Gauge": "CRMS0638", "corr": 0.98, "MAE": 0.47, "RMSE": 0.58, "NSE": 0.33 }, "geometry": { "type": "Point", "coordinates": [ -93.510571208621656, 29.868002323972494 ] } },
{ "type": "Feature", "properties": { "Gauge": "CRMS1743", "corr": 0.23, "MAE": 0.63, "RMSE": 0.69, "NSE": -0.36 }, "geometry": { "type": "Point", "coordinates": [ -93.229316742743592, 29.889775338692637 ] } },
{ "type": "Feature", "properties": { "Gauge": "CRMS0685", "corr": 0.88, "MAE": 0.28, "RMSE": 0.34, "NSE": 0.64 }, "geometry": { "type": "Point", "coordinates": [ -93.385569308169167, 29.889774500066935 ] } },
{ "type": "Feature", "properties": { "Gauge": "CRMS0639", "corr": 0.76, "MAE": 0.86, "RMSE": 0.9, "NSE": -1.52 }, "geometry": { "type": "Point", "coordinates": [ -93.479321092408554, 29.889774065807757 ] } },
{ "type": "Feature", "properties": { "Gauge": "CRMS0693", "corr": 0.7, "MAE": 0.62, "RMSE": 0.67, "NSE": -2.07 }, "geometry": { "type": "Point", "coordinates": [ -93.635574708124693, 29.897032883640936 ] } },
{ "type": "Feature", "properties": { "Gauge": "CRMS0650", "corr": 0.68, "MAE": 0.48, "RMSE": 0.54, "NSE": 0.19 }, "geometry": { "type": "Point", "coordinates": [ -93.135566570187976, 29.918806662798115 ] } },
{ "type": "Feature", "properties": { "Gauge": "CRMS0635", "corr": 0.89, "MAE": 0.96, "RMSE": 0.98, "NSE": -3.17 }, "geometry": { "type": "Point", "coordinates": [ -93.479320897508515, 29.918808403181988 ] } },
{ "type": "Feature", "properties": { "Gauge": "CRMS0651", "corr": 0.88, "MAE": 0.78, "RMSE": 0.79, "NSE": -5.5 }, "geometry": { "type": "Point", "coordinates": [ -93.510572151575246, 29.962356201999715 ] } },
{ "type": "Feature", "properties": { "Gauge": "CRMS6302", "corr": 0.65, "MAE": 0.63, "RMSE": 0.72, "NSE": -1.21 }, "geometry": { "type": "Point", "coordinates": [ -93.422917225858541, 30.039968218302882 ] } }
]
}
