{
"type": "FeatureCollection",
"crs": { "type": "name", "properties": { "name": "urn:ogc:def:crs:OGC:1.3:CRS84" } },
"features": [
{ "type": "Feature", "properties": { "Gauge": "USGS 8017044", "FID": 2, "corr": 1.0, "MAE": 0.03, "RMSE": 0.05 }, "geometry": { "type": "Point", "coordinates": [ -93.247170630150137, 30.23771962612793, 0.0 ] } },
{ "type": "Feature", "properties": { "Gauge": "OneRain 12005", "FID": 3, "corr": 0.69, "MAE": 2.36, "RMSE": 2.57 }, "geometry": { "type": "Point", "coordinates": [ -93.166843445001135, 30.198317373083267, 9.0 ] } },
{ "type": "Feature", "properties": { "Gauge": "OneRain 12084", "FID": 7, "corr": 0.72, "MAE": 1.32, "RMSE": 2.44 }, "geometry": { "type": "Point", "coordinates": [ -93.038716217893523, 30.218187245207215, 16.0 ] } },
{ "type": "Feature", "properties": { "Gauge": "OneRain 12011", "FID": 6, "corr": 0.74, "MAE": 1.74, "RMSE": 2.26 }, "geometry": { "type": "Point", "coordinates": [ -93.080980465597833, 30.240677087013019, 13.0 ] } },
{ "type": "Feature", "properties": { "Gauge": "OneRain 12082", "FID": 13, "corr": 0.8, "MAE": 0.98, "RMSE": 1.2 }, "geometry": { "type": "Point", "coordinates": [ -93.12957495084845, 30.248589241649373, 16.0 ] } },
{ "type": "Feature", "properties": { "Gauge": "OneRain 12006", "FID": 14, "corr": 0.74, "MAE": 0.82, "RMSE": 1.03 }, "geometry": { "type": "Point", "coordinates": [ -93.122088583001116, 30.261420298375402, 9.0 ] } },
{ "type": "Feature", "properties": { "Gauge": "OneRain 12037", "FID": 15, "corr": 0.74, "MAE": 1.54, "RMSE": 1.63 }, "geometry": { "type": "Point", "coordinates": [ -93.172275622732883, 30.263827303232588, 17.0 ] } },
{ "type": "Feature", "properties": { "Gauge": "OneRain 12081", "FID": 11, "corr": 0.78, "MAE": 0.58, "RMSE": 0.82 }, "geometry": { "type": "Point", "coordinates": [ -93.081464941836373, 30.277908550403833, 16.0 ] } },
{ "type": "Feature", "properties": { "Gauge": "OneRain 12080", "FID": 13, "corr": 0.73, "MAE": 1.21, "RMSE": 1.82 }, "geometry": { "type": "Point", "coordinates": [ -93.058483167499034, 30.287309156891332, 15.0 ] } },
{ "type": "Feature", "properties": { "Gauge": "OneRain 12016", "FID": 16, "corr": 0.67, "MAE": 0.57, "RMSE": 0.82 }, "geometry": { "type": "Point", "coordinates": [ -93.170111720531878, 30.329002937496373, 26.0 ] } },
{ "type": "Feature", "properties": { "Gauge": "OneRain 12079", "FID": 23, "corr": 0.69, "MAE": 1.3, "RMSE": 1.61 }, "geometry": { "type": "Point", "coordinates": [ -93.071762634712073, 30.330275845960102, 10.0 ] } },
{ "type": "Feature", "properties": { "Gauge": "OneRain 12018", "FID": 18, "corr": 0.24, "MAE": 3.07, "RMSE": 3.84 }, "geometry": { "type": "Point", "coordinates": [ -93.152030348775654, 30.398313704927808, 19.0 ] } },
{ "type": "Feature", "properties": { "Gauge": "OneRain 12077", "FID": 19, "corr": 0.72, "MAE": 0.61, "RMSE": 0.78 }, "geometry": { "type": "Point", "coordinates": [ -93.205075956845931, 30.300453717772715, 15.0 ] } },
{ "type": "Feature", "properties": { "Gauge": "OneRain 12078", "FID": 27, "corr": 0.41, "MAE": 0.66, "RMSE": 1.01 }, "geometry": { "type": "Point", "coordinates": [ -93.178842802240112, 30.302560294599495, 7.0 ] } }
]
}
