{
"type": "FeatureCollection",
"crs": { "type": "name", "properties": { "name": "urn:ogc:def:crs:OGC:1.3:CRS84" } },
"features": [
{ "type": "Feature", "properties": { "Gauge": "OneRain 12005", "FID": 3, "corr": 0.95, "MAE": 1.12, "RMSE": 1.31 }, "geometry": { "type": "Point", "coordinates": [ -93.166843445001135, 30.198317373083267, 9.0 ] } },
{ "type": "Feature", "properties": { "Gauge": "OneRain 12084", "FID": 7, "corr": 0.96, "MAE": 0.31, "RMSE": 0.82 }, "geometry": { "type": "Point", "coordinates": [ -93.038716217893523, 30.218187245207215, 16.0 ] } },
{ "type": "Feature", "properties": { "Gauge": "OneRain 12069", "FID": 5, "corr": 0.9, "MAE": 2.23, "RMSE": 2.57 }, "geometry": { "type": "Point", "coordinates": [ -93.174550603612801, 30.227460795253307, 7.0 ] } },
{ "type": "Feature", "properties": { "Gauge": "OneRain 12011", "FID": 6, "corr": 0.98, "MAE": 1.7, "RMSE": 2.12 }, "geometry": { "type": "Point", "coordinates": [ -93.080980465597833, 30.240677087013019, 13.0 ] } },
{ "type": "Feature", "properties": { "Gauge": "OneRain 12083", "FID": 10, "corr": 0.96, "MAE": 0.99, "RMSE": 1.26 }, "geometry": { "type": "Point", "coordinates": [ -93.068111, 30.236693999999488, 12.0 ] } },
{ "type": "Feature", "properties": { "Gauge": "OneRain 12082", "FID": 13, "corr": 0.98, "MAE": 1.03, "RMSE": 1.05 }, "geometry": { "type": "Point", "coordinates": [ -93.12957495084845, 30.248589241649373, 16.0 ] } },
{ "type": "Feature", "properties": { "Gauge": "OneRain 12006", "FID": 14, "corr": 0.99, "MAE": 1.13, "RMSE": 1.15 }, "geometry": { "type": "Point", "coordinates": [ -93.122088583001116, 30.261420298375402, 9.0 ] } },
{ "type": "Feature", "properties": { "Gauge": "OneRain 12037", "FID": 15, "corr": 0.79, "MAE": 0.72, "RMSE": 0.87 }, "geometry": { "type": "Point", "coordinates": [ -93.172275622732883, 30.263827303232588, 17.0 ] } },
{ "type": "Feature", "properties": { "Gauge": "OneRain 12081", "FID": 11, "corr": 0.95, "MAE": 0.99, "RMSE": 1.13 }, "geometry": { "type": "Point", "coordinates": [ -93.081464941836373, 30.277908550403833, 16.0 ] } },
{ "type": "Feature", "properties": { "Gauge": "OneRain 12015", "FID": 12, "corr": 0.95, "MAE": 1.07, "RMSE": 1.17 }, "geometry": { "type": "Point", "coordinates": [ -93.09552395028318, 30.290627197060939, 12.0 ] } },
{ "type": "Feature", "properties": { "Gauge": "OneRain 12080", "FID": 13, "corr": 0.98, "MAE": 0.3, "RMSE": 0.51 }, "geometry": { "type": "Point", "coordinates": [ -93.058483167499034, 30.287309156891332, 15.0 ] } },
{ "type": "Feature", "properties": { "Gauge": "OneRain 12030", "FID": 19, "corr": 0.96, "MAE": 1.55, "RMSE": 1.64 }, "geometry": { "type": "Point", "coordinates": [ -93.118169856010894, 30.297126452383232, 9.0 ] } },
{ "type": "Feature", "properties": { "Gauge": "OneRain 12014", "FID": 21, "corr": 0.98, "MAE": 1.1, "RMSE": 1.26 }, "geometry": { "type": "Point", "coordinates": [ -93.065606109816926, 30.308330349984438, 13.0 ] } },
{ "type": "Feature", "properties": { "Gauge": "OneRain 12016", "FID": 16, "corr": 0.97, "MAE": 0.36, "RMSE": 0.49 }, "geometry": { "type": "Point", "coordinates": [ -93.170111720531878, 30.329002937496373, 26.0 ] } },
{ "type": "Feature", "properties": { "Gauge": "OneRain 12079", "FID": 23, "corr": 0.98, "MAE": 1.12, "RMSE": 1.31 }, "geometry": { "type": "Point", "coordinates": [ -93.071762634712073, 30.330275845960102, 10.0 ] } },
{ "type": "Feature", "properties": { "Gauge": "OneRain 12018", "FID": 18, "corr": 0.89, "MAE": 1.04, "RMSE": 1.7 }, "geometry": { "type": "Point", "coordinates": [ -93.152030348775654, 30.398313704927808, 19.0 ] } },
{ "type": "Feature", "properties": { "Gauge": "OneRain 12077", "FID": 19, "corr": 0.92, "MAE": 0.95, "RMSE": 1.15 }, "geometry": { "type": "Point", "coordinates": [ -93.205030366465195, 30.300475749732424, 15.0 ] } },
{ "type": "Feature", "properties": { "Gauge": "OneRain 12134", "FID": 25, "corr": 0.93, "MAE": 1.81, "RMSE": 1.86 }, "geometry": { "type": "Point", "coordinates": [ -93.151, 30.306092569999464, 0.0 ] } },
{ "type": "Feature", "properties": { "Gauge": "OneRain 12096", "FID": 27, "corr": 0.95, "MAE": 0.54, "RMSE": 0.71 }, "geometry": { "type": "Point", "coordinates": [ -93.125631489855166, 30.351923170632855, 0.0 ] } },
{ "type": "Feature", "properties": { "Gauge": "OneRain 12012", "FID": 28, "corr": 0.96, "MAE": 0.69, "RMSE": 0.85 }, "geometry": { "type": "Point", "coordinates": [ -93.118614647309826, 30.19795686560391, 14.0 ] } },
{ "type": "Feature", "properties": { "Gauge": "OneRain 12010", "FID": 29, "corr": 0.95, "MAE": 0.8, "RMSE": 1.31 }, "geometry": { "type": "Point", "coordinates": [ -93.019302520347921, 30.241156667025603, 18.0 ] } }
]
}
