{
"type": "FeatureCollection",
"crs": { "type": "name", "properties": { "name": "urn:ogc:def:crs:OGC:1.3:CRS84" } },
"features": [
{ "type": "Feature", "properties": { "Gauge": "USGS 8017044", "FID": 2, "corr": 1.0, "MAE": 0.11, "RMSE": 0.12 }, "geometry": { "type": "Point", "coordinates": [ -93.247170630150137, 30.23771962612793, 0.0 ] } },
{ "type": "Feature", "properties": { "Gauge": "OneRain 12005", "FID": 3, "corr": 0.92, "MAE": 1.01, "RMSE": 1.31 }, "geometry": { "type": "Point", "coordinates": [ -93.166843445001135, 30.198317373083267, 9.0 ] } },
{ "type": "Feature", "properties": { "Gauge": "OneRain 12084", "FID": 7, "corr": 0.91, "MAE": 2.68, "RMSE": 3.35 }, "geometry": { "type": "Point", "coordinates": [ -93.038716217893523, 30.218187245207215, 16.0 ] } },
{ "type": "Feature", "properties": { "Gauge": "OneRain 12069", "FID": 5, "corr": 0.89, "MAE": 1.02, "RMSE": 1.38 }, "geometry": { "type": "Point", "coordinates": [ -93.174550603612801, 30.227460795253307, 7.0 ] } },
{ "type": "Feature", "properties": { "Gauge": "OneRain 12083", "FID": 10, "corr": 0.99, "MAE": 1.59, "RMSE": 1.67 }, "geometry": { "type": "Point", "coordinates": [ -93.068111, 30.236693999999488, 12.0 ] } },
{ "type": "Feature", "properties": { "Gauge": "OneRain 12082", "FID": 13, "corr": 0.91, "MAE": 2.55, "RMSE": 2.71 }, "geometry": { "type": "Point", "coordinates": [ -93.12957495084845, 30.248589241649373, 16.0 ] } },
{ "type": "Feature", "properties": { "Gauge": "OneRain 12006", "FID": 14, "corr": 0.8, "MAE": 0.98, "RMSE": 1.07 }, "geometry": { "type": "Point", "coordinates": [ -93.122088583001116, 30.261420298375402, 9.0 ] } },
{ "type": "Feature", "properties": { "Gauge": "OneRain 12081", "FID": 11, "corr": 0.96, "MAE": 0.43, "RMSE": 0.66 }, "geometry": { "type": "Point", "coordinates": [ -93.081464941836373, 30.277908550403833, 16.0 ] } },
{ "type": "Feature", "properties": { "Gauge": "OneRain 12080", "FID": 13, "corr": 0.98, "MAE": 2.08, "RMSE": 2.17 }, "geometry": { "type": "Point", "coordinates": [ -93.058483167499034, 30.287309156891332, 15.0 ] } },
{ "type": "Feature", "properties": { "Gauge": "OneRain 12016", "FID": 16, "corr": 0.99, "MAE": 0.76, "RMSE": 0.82 }, "geometry": { "type": "Point", "coordinates": [ -93.170111720531878, 30.329002937496373, 26.0 ] } },
{ "type": "Feature", "properties": { "Gauge": "OneRain 12079", "FID": 23, "corr": 0.99, "MAE": 1.32, "RMSE": 1.47 }, "geometry": { "type": "Point", "coordinates": [ -93.071762634712073, 30.330275845960102, 10.0 ] } },
{ "type": "Feature", "properties": { "Gauge": "OneRain 12077", "FID": 19, "corr": 0.88, "MAE": 1.16, "RMSE": 1.37 }, "geometry": { "type": "Point", "coordinates": [ -93.205030366465195, 30.300475749732424, 15.0 ] } },
{ "type": "Feature", "properties": { "Gauge": "OneRain 12078", "FID": 27, "corr": 0.91, "MAE": 2.88, "RMSE": 3.0 }, "geometry": { "type": "Point", "coordinates": [ -93.178842802240112, 30.302560294599495, 7.0 ] } },
{ "type": "Feature", "properties": { "Gauge": "OneRain 12068", "FID": 21, "corr": 0.97, "MAE": 0.57, "RMSE": 0.69 }, "geometry": { "type": "Point", "coordinates": [ -93.168379464540749, 30.176700322739432, 13.0 ] } },
{ "type": "Feature", "properties": { "Gauge": "OneRain 12070", "FID": 31, "corr": 0.9, "MAE": 0.95, "RMSE": 0.97 }, "geometry": { "type": "Point", "coordinates": [ -93.251294065010129, 30.262972592830003, 5.0 ] } },
{ "type": "Feature", "properties": { "Gauge": "OneRain 12012", "FID": 28, "corr": 0.88, "MAE": 2.66, "RMSE": 3.03 }, "geometry": { "type": "Point", "coordinates": [ -93.118614647309826, 30.19795686560391, 14.0 ] } }
]
}
