{
"type": "FeatureCollection",
"crs": { "type": "name", "properties": { "name": "urn:ogc:def:crs:OGC:1.3:CRS84" } },
"features": [
{ "type": "Feature", "properties": { "Gauge": "OneRain 12034", "corr": 0.56, "MAE": 1.15, "RMSE": 2.38 }, "geometry": { "type": "Point", "coordinates": [ -93.240801577229576, 30.205776599196991, 2.999993999980978 ] } },
{ "type": "Feature", "properties": { "Gauge": "OneRain 12035", "corr": 0.45, "MAE": 4.23, "RMSE": 6.77 }, "geometry": { "type": "Point", "coordinates": [ -93.213879712976862, 30.177244066130395, 10.999977999977999 ] } },
{ "type": "Feature", "properties": { "Gauge": "OneRain 12036", "corr": 0.48, "MAE": 3.58, "RMSE": 5.82 }, "geometry": { "type": "Point", "coordinates": [ -93.237549921736971, 30.176298057034181, 7.99998399999702 ] } },
{ "type": "Feature", "properties": { "Gauge": "OneRain 12067", "corr": 0.75, "MAE": 3.06, "RMSE": 4.69 }, "geometry": { "type": "Point", "coordinates": [ -93.214005524496386, 30.160857706660668, 12.0 ] } },
{ "type": "Feature", "properties": { "Gauge": "OneRain 12130 DS", "corr": 0.73, "MAE": 0.48, "RMSE": 1.32 }, "geometry": { "type": "Point", "coordinates": [ -93.198446856534218, 30.256971898208203, 0.0 ] } },
{ "type": "Feature", "properties": { "Gauge": "OneRain 12130 US", "corr": 0.66, "MAE": 0.65, "RMSE": 1.82 }, "geometry": { "type": "Point", "coordinates": [ -93.198356295436071, 30.256938342381265, 0.0 ] } },
{ "type": "Feature", "properties": { "Gauge": "OneRain 12135 DS", "corr": 0.97, "MAE": 0.07, "RMSE": 0.15 }, "geometry": { "type": "Point", "coordinates": [ -93.221464806720491, 30.223716125588098, 0.0 ] } },
{ "type": "Feature", "properties": { "Gauge": "OneRain 12135 US", "corr": 0.09, "MAE": 1.35, "RMSE": 3.04 }, "geometry": { "type": "Point", "coordinates": [ -93.221286550722184, 30.223707019997953, 0.0 ] } },
{ "type": "Feature", "properties": { "Gauge": "OneRain 12147", "corr": 0.7, "MAE": 3.32, "RMSE": 5.2 }, "geometry": { "type": "Point", "coordinates": [ -93.225145284837254, 30.169723277736903, 0.0 ] } }
]
}
