{
"type": "FeatureCollection",
"crs": { "type": "name", "properties": { "name": "urn:ogc:def:crs:OGC:1.3:CRS84" } },
"features": [
{ "type": "Feature", "properties": { "Gauge": "USGS 8017044", "FID": 2, "corr": 1.0, "MAE": 0.1, "RMSE": 0.11 }, "geometry": { "type": "Point", "coordinates": [ -93.247170630150137, 30.23771962612793, 0.0 ] } },
{ "type": "Feature", "properties": { "Gauge": "OneRain 12005", "FID": 3, "corr": 0.91, "MAE": 1.2, "RMSE": 1.48 }, "geometry": { "type": "Point", "coordinates": [ -93.166843445001135, 30.198317373083267, 9.0 ] } },
{ "type": "Feature", "properties": { "Gauge": "OneRain 12084", "FID": 7, "corr": 0.86, "MAE": 3.51, "RMSE": 4.25 }, "geometry": { "type": "Point", "coordinates": [ -93.038716217893523, 30.218187245207215, 16.0 ] } },
{ "type": "Feature", "properties": { "Gauge": "OneRain 12069", "FID": 5, "corr": 0.87, "MAE": 1.59, "RMSE": 1.99 }, "geometry": { "type": "Point", "coordinates": [ -93.174550603612801, 30.227460795253307, 7.0 ] } },
{ "type": "Feature", "properties": { "Gauge": "OneRain 12083", "FID": 10, "corr": 0.98, "MAE": 0.86, "RMSE": 1.11 }, "geometry": { "type": "Point", "coordinates": [ -93.068111, 30.236693999999488, 12.0 ] } },
{ "type": "Feature", "properties": { "Gauge": "OneRain 12082", "FID": 13, "corr": 0.9, "MAE": 1.12, "RMSE": 1.35 }, "geometry": { "type": "Point", "coordinates": [ -93.12957495084845, 30.248589241649373, 16.0 ] } },
{ "type": "Feature", "properties": { "Gauge": "OneRain 12006", "FID": 14, "corr": 0.79, "MAE": 1.14, "RMSE": 1.28 }, "geometry": { "type": "Point", "coordinates": [ -93.122088583001116, 30.261420298375402, 9.0 ] } },
{ "type": "Feature", "properties": { "Gauge": "OneRain 12081", "FID": 11, "corr": 0.93, "MAE": 0.94, "RMSE": 1.25 }, "geometry": { "type": "Point", "coordinates": [ -93.081464941836373, 30.277908550403833, 16.0 ] } },
{ "type": "Feature", "properties": { "Gauge": "OneRain 12080", "FID": 13, "corr": 0.97, "MAE": 1.63, "RMSE": 1.8 }, "geometry": { "type": "Point", "coordinates": [ -93.058483167499034, 30.287309156891332, 15.0 ] } },
{ "type": "Feature", "properties": { "Gauge": "OneRain 12016", "FID": 16, "corr": 0.98, "MAE": 0.79, "RMSE": 0.9 }, "geometry": { "type": "Point", "coordinates": [ -93.170111720531878, 30.329002937496373, 26.0 ] } },
{ "type": "Feature", "properties": { "Gauge": "OneRain 12079", "FID": 23, "corr": 0.92, "MAE": 1.07, "RMSE": 1.29 }, "geometry": { "type": "Point", "coordinates": [ -93.071762634712073, 30.330275845960102, 10.0 ] } },
{ "type": "Feature", "properties": { "Gauge": "OneRain 12077", "FID": 19, "corr": 0.86, "MAE": 1.54, "RMSE": 1.7 }, "geometry": { "type": "Point", "coordinates": [ -93.205030366465195, 30.300475749732424, 15.0 ] } },
{ "type": "Feature", "properties": { "Gauge": "OneRain 12078", "FID": 27, "corr": 0.85, "MAE": 0.98, "RMSE": 1.17 }, "geometry": { "type": "Point", "coordinates": [ -93.178842802240112, 30.302560294599495, 7.0 ] } },
{ "type": "Feature", "properties": { "Gauge": "OneRain 12068", "FID": 21, "corr": 0.95, "MAE": 1.12, "RMSE": 1.3 }, "geometry": { "type": "Point", "coordinates": [ -93.168379464540749, 30.176700322739432, 13.0 ] } },
{ "type": "Feature", "properties": { "Gauge": "OneRain 12012", "FID": 28, "corr": 0.83, "MAE": 3.49, "RMSE": 3.89 }, "geometry": { "type": "Point", "coordinates": [ -93.118614647309826, 30.19795686560391, 14.0 ] } }
]
}
