{
"type": "FeatureCollection",
"crs": { "type": "name", "properties": { "name": "urn:ogc:def:crs:OGC:1.3:CRS84" } },
"features": [
{ "type": "Feature", "properties": { "Gauge": "USGS 8017044", "FID": 2, "corr": 1.0, "MAE": 0.03, "RMSE": 0.04 }, "geometry": { "type": "Point", "coordinates": [ -93.247170630150137, 30.23771962612793, 0.0 ] } },
{ "type": "Feature", "properties": { "Gauge": "OneRain 12005", "FID": 3, "corr": -0.38, "MAE": 2.1, "RMSE": 2.24 }, "geometry": { "type": "Point", "coordinates": [ -93.166843445001135, 30.198317373083267, 9.0 ] } },
{ "type": "Feature", "properties": { "Gauge": "OneRain 12084", "FID": 7, "corr": 0.99, "MAE": 1.41, "RMSE": 1.46 }, "geometry": { "type": "Point", "coordinates": [ -93.038716217893523, 30.218187245207215, 16.0 ] } },
{ "type": "Feature", "properties": { "Gauge": "OneRain 12069", "FID": 5, "corr": 0.15, "MAE": 0.6, "RMSE": 0.81 }, "geometry": { "type": "Point", "coordinates": [ -93.174550603612801, 30.227460795253307, 7.0 ] } },
{ "type": "Feature", "properties": { "Gauge": "OneRain 12011", "FID": 6, "corr": 0.19, "MAE": 0.66, "RMSE": 0.74 }, "geometry": { "type": "Point", "coordinates": [ -93.080980465597833, 30.240677087013019, 13.0 ] } },
{ "type": "Feature", "properties": { "Gauge": "OneRain 12082", "FID": 13, "corr": 0.95, "MAE": 1.3, "RMSE": 1.33 }, "geometry": { "type": "Point", "coordinates": [ -93.12957495084845, 30.248589241649373, 16.0 ] } },
{ "type": "Feature", "properties": { "Gauge": "OneRain 12006", "FID": 14, "corr": 0.95, "MAE": 1.46, "RMSE": 1.52 }, "geometry": { "type": "Point", "coordinates": [ -93.122088583001116, 30.261420298375402, 9.0 ] } },
{ "type": "Feature", "properties": { "Gauge": "OneRain 12037", "FID": 15, "corr": 0.92, "MAE": 0.85, "RMSE": 0.91 }, "geometry": { "type": "Point", "coordinates": [ -93.172275622732883, 30.263827303232588, 17.0 ] } },
{ "type": "Feature", "properties": { "Gauge": "OneRain 12081", "FID": 11, "corr": 0.85, "MAE": 1.54, "RMSE": 1.59 }, "geometry": { "type": "Point", "coordinates": [ -93.081464941836373, 30.277908550403833, 16.0 ] } },
{ "type": "Feature", "properties": { "Gauge": "OneRain 12015", "FID": 12, "corr": 0.91, "MAE": 1.24, "RMSE": 1.41 }, "geometry": { "type": "Point", "coordinates": [ -93.09552395028318, 30.290627197060939, 12.0 ] } },
{ "type": "Feature", "properties": { "Gauge": "OneRain 12080", "FID": 13, "corr": 0.89, "MAE": 0.63, "RMSE": 0.79 }, "geometry": { "type": "Point", "coordinates": [ -93.058483167499034, 30.287309156891332, 15.0 ] } },
{ "type": "Feature", "properties": { "Gauge": "OneRain 12014", "FID": 21, "corr": 0.81, "MAE": 8.21, "RMSE": 8.29 }, "geometry": { "type": "Point", "coordinates": [ -93.065606109816926, 30.308330349984438, 13.0 ] } },
{ "type": "Feature", "properties": { "Gauge": "OneRain 12016", "FID": 16, "corr": 0.76, "MAE": 1.86, "RMSE": 1.88 }, "geometry": { "type": "Point", "coordinates": [ -93.170111720531878, 30.329002937496373, 26.0 ] } },
{ "type": "Feature", "properties": { "Gauge": "OneRain 12079", "FID": 23, "corr": 0.85, "MAE": 2.26, "RMSE": 2.54 }, "geometry": { "type": "Point", "coordinates": [ -93.071762634712073, 30.330275845960102, 10.0 ] } },
{ "type": "Feature", "properties": { "Gauge": "OneRain 12018", "FID": 18, "corr": 0.86, "MAE": 1.29, "RMSE": 1.33 }, "geometry": { "type": "Point", "coordinates": [ -93.152030348775654, 30.398313704927808, 19.0 ] } },
{ "type": "Feature", "properties": { "Gauge": "OneRain 12077", "FID": 19, "corr": 0.43, "MAE": 0.73, "RMSE": 1.2 }, "geometry": { "type": "Point", "coordinates": [ -93.205075956845931, 30.300453717772715, 15.0 ] } },
{ "type": "Feature", "properties": { "Gauge": "OneRain 12078", "FID": 27, "corr": 0.9, "MAE": 2.14, "RMSE": 2.17 }, "geometry": { "type": "Point", "coordinates": [ -93.178842802240112, 30.302560294599495, 7.0 ] } },
{ "type": "Feature", "properties": { "Gauge": "OneRain 12068", "FID": 21, "corr": 0.93, "MAE": 0.58, "RMSE": 0.72 }, "geometry": { "type": "Point", "coordinates": [ -93.168379464540749, 30.176700322739432, 13.0 ] } },
{ "type": "Feature", "properties": { "Gauge": "OneRain 12070", "FID": 31, "corr": 0.83, "MAE": 2.71, "RMSE": 2.74 }, "geometry": { "type": "Point", "coordinates": [ -93.251294065010129, 30.262972592830003, 5.0 ] } }
]
}
