{
"type": "FeatureCollection",
"crs": { "type": "name", "properties": { "name": "urn:ogc:def:crs:OGC:1.3:CRS84" } },
"features": [
{ "type": "Feature", "properties": { "Gauge": "OneRain 12034", "corr": 1.0, "MAE": 0.01, "RMSE": 0.04 }, "geometry": { "type": "Point", "coordinates": [ -93.240801577229576, 30.205776599196991, 2.999993999980978 ] } },
{ "type": "Feature", "properties": { "Gauge": "OneRain 12035", "corr": 0.84, "MAE": 0.41, "RMSE": 0.66 }, "geometry": { "type": "Point", "coordinates": [ -93.213879712976862, 30.177244066130395, 10.999977999977999 ] } },
{ "type": "Feature", "properties": { "Gauge": "OneRain 12036", "corr": 0.88, "MAE": 0.35, "RMSE": 0.53 }, "geometry": { "type": "Point", "coordinates": [ -93.237549921736971, 30.176298057034181, 7.99998399999702 ] } },
{ "type": "Feature", "properties": { "Gauge": "OneRain 12067", "corr": 0.91, "MAE": 0.26, "RMSE": 0.44 }, "geometry": { "type": "Point", "coordinates": [ -93.214554672485619, 30.160626004074878, 4.202091333310951 ] } }
]
}
