{
"type": "FeatureCollection",
"crs": { "type": "name", "properties": { "name": "urn:ogc:def:crs:OGC:1.3:CRS84" } },
"features": [
{ "type": "Feature", "properties": { "Gauge": "USGS08026000", "corr": 0.98, "MAE": 2.09, "RMSE": 2.23 }, "geometry": { "type": "Point", "coordinates": [ -93.519539307296952, 31.064143257578394, 0.0 ] } },
{ "type": "Feature", "properties": { "Gauge": "USGS08030540", "corr": 0.5, "MAE": 0.48, "RMSE": 0.57 }, "geometry": { "type": "Point", "coordinates": [ -93.72084874240268, 30.097002337242547, 0.0 ] } },
{ "type": "Feature", "properties": { "Gauge": "USGS08028000", "corr": 0.92, "MAE": 2.94, "RMSE": 3.16 }, "geometry": { "type": "Point", "coordinates": [ -93.353733776126234, 30.953009662590738, 0.0 ] } },
{ "type": "Feature", "properties": { "Gauge": "USGS08025500", "corr": 0.91, "MAE": 1.53, "RMSE": 2.34 }, "geometry": { "type": "Point", "coordinates": [ -93.515664139680723, 31.307111344321303, 0.0 ] } },
{ "type": "Feature", "properties": { "Gauge": "USGS08028500", "corr": 0.96, "MAE": 1.63, "RMSE": 1.96 }, "geometry": { "type": "Point", "coordinates": [ -93.608282714743922, 30.747475846598618, 0.0 ] } },
{ "type": "Feature", "properties": { "Gauge": "USGS08030500", "corr": 0.98, "MAE": 0.93, "RMSE": 0.95 }, "geometry": { "type": "Point", "coordinates": [ -93.743878558970962, 30.303826718987583, 0.0 ] } },
{ "type": "Feature", "properties": { "Gauge": "CRMS0658", "corr": 0.93, "MAE": 0.78, "RMSE": 0.8 }, "geometry": { "type": "Point", "coordinates": [ -93.604319148789358, 30.056705264221538, 0.0 ] } },
{ "type": "Feature", "properties": { "Gauge": "CRMS0697", "corr": 0.68, "MAE": 0.19, "RMSE": 0.24 }, "geometry": { "type": "Point", "coordinates": [ -93.666981512037566, 30.064174469793667, 0.0 ] } }
]
}
